pyaoa/__init__.py
pyaoa/aoa.py
pyaoa-0.2.dist-info/METADATA
pyaoa-0.2.dist-info/WHEEL
pyaoa-0.2.dist-info/top_level.txt
pyaoa-0.2.dist-info/RECORD
